{
    "$schema": "../workload_schema.json",
    "sections": [
        {
            "inserts": {
                "amount": 10,
                "key_len": 1,
                "val_len": 5
            }
        },
        {
            "point_queries": {
                "amount": 50
            },
            "range_queries": {
                "amount": 50,
                "selectivity": 0.5
            },
            "updates": {
                "amount": 50,
                "val_len": 10
            },
            "deletes": {
                "amount": 50
            }
        }
    ]
}
